pth2onnx/__init__.py
pth2onnx/__main__.py
pth2onnx/config.yml
pth2onnx/logconf.yml
pth2onnx/version.py
pth2onnx/app/app.py
pth2onnx/app/common.py
pth2onnx/app/convert/yolox.py
pth2onnx/scripts/pth2onnx
pth2onnx/scripts/pth2onnx.bat
pth2onnx-0.0.4.dist-info/LICENSE
pth2onnx-0.0.4.dist-info/METADATA
pth2onnx-0.0.4.dist-info/WHEEL
pth2onnx-0.0.4.dist-info/entry_points.txt
pth2onnx-0.0.4.dist-info/top_level.txt
pth2onnx-0.0.4.dist-info/RECORD
