Metadata-Version: 2.1
Name: pth2onnx
Version: 0.0.4
Summary: pth2onnx: Convert PyTorch model to Onnx model.
Home-page: https://github.com/hamacom2004jp/pth2onnx
Download-URL: https://github.com/hamacom2004jp/pth2onnx
Author: hamacom2004jp
Author-email: hamacom2004jp@gmail.com
Maintainer: hamacom2004jp
Maintainer-email: hamacom2004jp@gmail.com
License: MIT
Keywords: pytorch onnx convert image ai model
Classifier: Development Status :: 4 - Beta
Classifier: Intended Audience :: Developers
Classifier: Intended Audience :: Information Technology
Classifier: Intended Audience :: System Administrators
Classifier: License :: OSI Approved :: MIT License
Classifier: Natural Language :: Japanese
Classifier: Programming Language :: Python
Classifier: Topic :: Utilities
License-File: LICENSE
Requires-Dist: numpy
Requires-Dist: opencv-python
Requires-Dist: Pillow
Requires-Dist: PyYAML
Requires-Dist: requests
Requires-Dist: tabulate
Requires-Dist: twine
Requires-Dist: wheel
